<annotation>
	<folder>indy-corrected-background</folder>
	<filename>45.jpg</filename>
	<path>E:\Eigene Dateien\FH\Master\3. Semester\DIP\DIP-Project\indy-corrected-background\45.jpg</path>
	<source>
		<database>Unknown</database>
	</source>
	<size>
		<width>124</width>
		<height>216</height>
		<depth>3</depth>
	</size>
	<segmented>0</segmented>
	<object>
		<name>Hat</name>
		<pose>Unspecified</pose>
		<truncated>0</truncated>
		<difficult>0</difficult>
		<bndbox>
			<xmin>19</xmin>
			<ymin>4</ymin>
			<xmax>112</xmax>
			<ymax>53</ymax>
		</bndbox>
	</object>
	<object>
		<name>Face</name>
		<pose>Unspecified</pose>
		<truncated>0</truncated>
		<difficult>0</difficult>
		<bndbox>
			<xmin>36</xmin>
			<ymin>42</ymin>
			<xmax>90</xmax>
			<ymax>81</ymax>
		</bndbox>
	</object>
	<object>
		<name>Bodyprint</name>
		<pose>Unspecified</pose>
		<truncated>0</truncated>
		<difficult>0</difficult>
		<bndbox>
			<xmin>29</xmin>
			<ymin>72</ymin>
			<xmax>94</xmax>
			<ymax>140</ymax>
		</bndbox>
	</object>
	<object>
		<name>Left Leg</name>
		<pose>Unspecified</pose>
		<truncated>0</truncated>
		<difficult>0</difficult>
		<bndbox>
			<xmin>20</xmin>
			<ymin>135</ymin>
			<xmax>56</xmax>
			<ymax>207</ymax>
		</bndbox>
	</object>
	<object>
		<name>Right Leg</name>
		<pose>Unspecified</pose>
		<truncated>0</truncated>
		<difficult>0</difficult>
		<bndbox>
			<xmin>55</xmin>
			<ymin>136</ymin>
			<xmax>92</xmax>
			<ymax>210</ymax>
		</bndbox>
	</object>
	<object>
		<name>Left Arm</name>
		<pose>Unspecified</pose>
		<truncated>0</truncated>
		<difficult>0</difficult>
		<bndbox>
			<xmin>7</xmin>
			<ymin>77</ymin>
			<xmax>37</xmax>
			<ymax>132</ymax>
		</bndbox>
	</object>
	<object>
		<name>Right Arm</name>
		<pose>Unspecified</pose>
		<truncated>0</truncated>
		<difficult>0</difficult>
		<bndbox>
			<xmin>85</xmin>
			<ymin>78</ymin>
			<xmax>116</xmax>
			<ymax>132</ymax>
		</bndbox>
	</object>
	<object>
		<name>Right Hand</name>
		<pose>Unspecified</pose>
		<truncated>0</truncated>
		<difficult>0</difficult>
		<bndbox>
			<xmin>91</xmin>
			<ymin>124</ymin>
			<xmax>120</xmax>
			<ymax>159</ymax>
		</bndbox>
	</object>
</annotation>
